pybounds/__init__.py
pybounds/jacobian.py
pybounds/observability.py
pybounds/simulator.py
pybounds/util.py
pybounds-0.1.0.dist-info/licenses/LICENSE
pybounds-0.1.0.dist-info/METADATA
pybounds-0.1.0.dist-info/WHEEL
pybounds-0.1.0.dist-info/top_level.txt
pybounds-0.1.0.dist-info/RECORD
