Metadata-Version: 2.4
Name: pybounds
Version: 0.1.0
Summary: Bounding Observability for Uncertain Nonlinear Dynamics Systems (BOUNDS)
Home-page: https://pypi.org/project/pybounds/
Author: Ben Cellini, Burak Boyacioglu, Floris van Breugel
Author-email: bcellini00@gmail.com
Classifier: Programming Language :: Python :: 3
Classifier: License :: OSI Approved :: MIT License
Classifier: Operating System :: OS Independent
Requires-Python: >=3.0
License-File: LICENSE
Dynamic: author
Dynamic: author-email
Dynamic: classifier
Dynamic: description
Dynamic: description-content-type
Dynamic: home-page
Dynamic: license-file
Dynamic: requires-python
Dynamic: summary
